[
	{
		"url": "https://www.zjsnrwiki.com/images/1/16/L_NORMAL_7_3.png",
		"filename": "L NORMAL 7 3.png"
	},
	{
		"url": "https://www.zjsnrwiki.com/images/2/26/L_BROKEN_7_3.png",
		"filename": "L BROKEN 7 3.png"
	},
	{
		"url": "https://www.zjsnrwiki.com/images/c/cb/L_NORMAL_7_4.png",
		"filename": "L NORMAL 7 4.png"
	},
	{
		"url": "https://www.zjsnrwiki.com/images/b/bf/L_BROKEN_7_4.png",
		"filename": "L BROKEN 7 4.png"
	},
	{
		"url": "https://www.zjsnrwiki.com/images/8/84/L_NORMAL_61_1.png",
		"filename": "L NORMAL 61 1.png"
	},
	{
		"url": "https://www.zjsnrwiki.com/images/0/03/L_BROKEN_61_1.png",
		"filename": "L BROKEN 61 1.png"
	},
	{
		"url": "https://www.zjsnrwiki.com/images/6/6d/L_NORMAL_61_2.png",
		"filename": "L NORMAL 61 2.png"
	},
	{
		"url": "https://www.zjsnrwiki.com/images/1/19/L_BROKEN_61_2.png",
		"filename": "L BROKEN 61 2.png"
	},
	{
		"url": "https://www.zjsnrwiki.com/images/c/cf/L_NORMAL_105_2.png",
		"filename": "L NORMAL 105 2.png"
	},
	{
		"url": "https://www.zjsnrwiki.com/images/d/d1/L_BROKEN_105_2.png",
		"filename": "L BROKEN 105 2.png"
	},
	{
		"url": "https://www.zjsnrwiki.com/images/1/19/L_NORMAL_157_1.png",
		"filename": "L NORMAL 157 1.png"
	},
	{
		"url": "https://www.zjsnrwiki.com/images/9/97/L_BROKEN_157_1.png",
		"filename": "L BROKEN 157 1.png"
	},
	{
		"url": "https://www.zjsnrwiki.com/images/1/10/L_NORMAL_299_1.png",
		"filename": "L NORMAL 299 1.png"
	},
	{
		"url": "https://www.zjsnrwiki.com/images/a/ae/L_BROKEN_299_1.png",
		"filename": "L BROKEN 299 1.png"
	}
]